app/__init__.py
app/main.py
cronjob_cboe-0.2.1.dist-info/WHEEL
cronjob_cboe-0.2.1.dist-info/METADATA
cronjob_cboe-0.2.1.dist-info/RECORD
