Metadata-Version: 2.1
Name: cronjob-cboe
Version: 0.2.1
Summary: 
Author: Ernesto Martinez del Pino
Author-email: ernestomar1997@hotmail.com
Requires-Python: >=3.9,<4.0
Classifier: Programming Language :: Python :: 3
Classifier: Programming Language :: Python :: 3.10
Classifier: Programming Language :: Python :: 3.9
Requires-Dist: cboe-extractor (>=0.2.0,<0.3.0)
Requires-Dist: python-decouple (>=3.6,<4.0)
Requires-Dist: radar-mongodb (>=0.2.0,<0.3.0)
